pandas_usaddress/__init__.py
pandas_usaddress/abbreviations.csv
pandas_usaddress/numbered_streets.csv
pandas_usaddress/street_numbers.csv
pandas_usaddress-0.11.dist-info/METADATA
pandas_usaddress-0.11.dist-info/RECORD
pandas_usaddress-0.11.dist-info/WHEEL
pandas_usaddress-0.11.dist-info/top_level.txt
