Metadata-Version: 2.1
Name: pandas-usaddress
Version: 0.11
Summary: The usaddress library made easy with Pandas.
Home-page: https://github.com/Lyonk71/pandas-usaddress
Author: Keith Lyons
Author-email: lyonk71@gmail.com
License: MIT
Platform: UNKNOWN
Requires-Dist: pandas
Requires-Dist: usaddress
